{"openapi":"3.0.0","paths":{"/":{"get":{"operationId":"AppController_getHello","parameters":[],"responses":{"200":{"description":""}}}}},"info":{"title":"BFF (Aplicativo) - API","description":"Swagger Ancarx - BFF (Aplicativo) - API","version":"1.0","contact":{}},"tags":[],"servers":[{"url":"https://api.ancar.com.br/dev/api-bff-app/api/v1 - API de Dev"},{"url":"https://api.ancar.com.br/hml/api-bff-app/api/v1 - API de Homologação"},{"url":"https://api.ancar.com.br/prd/api-bff-app/api/v1 - API de Produção"}],"components":{"securitySchemes":{"authenticationtoken":{"type":"apiKey","in":"header","name":"authenticationtoken","description":"Token do API Gateway"},"token":{"type":"apiKey","in":"header","name":"token","description":"Token para clientes utilizado no ancarx-microservices (token, apiKey)"}},"schemas":{}}}